<?xml version="1.0" encoding="UTF-8" ?>
<!DOCTYPE mapper PUBLIC "-//mybatis.org//DTD Mapper 3.0//EN" "http://mybatis.org/dtd/mybatis-3-mapper.dtd" >
<mapper namespace="cn.carry.mapper.AccountMapper" >
  <resultMap id="BaseResultMap" type="cn.carry.domain.Account" >
    <!--
      WARNING - @mbggenerated
      This element is automatically generated by MyBatis Generator, do not modify.
    -->
    <id column="id" property="id" jdbcType="BIGINT" />
    <result column="tradePassword" property="tradepassword" jdbcType="VARCHAR" />
    <result column="usableAmount" property="usableamount" jdbcType="DECIMAL" />
    <result column="freezedAmount" property="freezedamount" jdbcType="DECIMAL" />
    <result column="borrowLimitAmount" property="borrowlimitamount" jdbcType="DECIMAL" />
    <result column="version" property="version" jdbcType="INTEGER" />
    <result column="unReceiveInterest" property="unreceiveinterest" jdbcType="DECIMAL" />
    <result column="unReceivePrincipal" property="unreceiveprincipal" jdbcType="DECIMAL" />
    <result column="unReturnAmount" property="unreturnamount" jdbcType="DECIMAL" />
    <result column="remainBorrowLimit" property="remainborrowlimit" jdbcType="DECIMAL" />
  </resultMap>
  <sql id="Example_Where_Clause" >
    <!--
      WARNING - @mbggenerated
      This element is automatically generated by MyBatis Generator, do not modify.
    -->
    <where >
      <foreach collection="oredCriteria" item="criteria" separator="or" >
        <if test="criteria.valid" >
          <trim prefix="(" suffix=")" prefixOverrides="and" >
            <foreach collection="criteria.criteria" item="criterion" >
              <choose >
                <when test="criterion.noValue" >
                  and ${criterion.condition}
                </when>
                <when test="criterion.singleValue" >
                  and ${criterion.condition} #{criterion.value}
                </when>
                <when test="criterion.betweenValue" >
                  and ${criterion.condition} #{criterion.value} and #{criterion.secondValue}
                </when>
                <when test="criterion.listValue" >
                  and ${criterion.condition}
                  <foreach collection="criterion.value" item="listItem" open="(" close=")" separator="," >
                    #{listItem}
                  </foreach>
                </when>
              </choose>
            </foreach>
          </trim>
        </if>
      </foreach>
    </where>
  </sql>
  <sql id="Update_By_Example_Where_Clause" >
    <!--
      WARNING - @mbggenerated
      This element is automatically generated by MyBatis Generator, do not modify.
    -->
    <where >
      <foreach collection="example.oredCriteria" item="criteria" separator="or" >
        <if test="criteria.valid" >
          <trim prefix="(" suffix=")" prefixOverrides="and" >
            <foreach collection="criteria.criteria" item="criterion" >
              <choose >
                <when test="criterion.noValue" >
                  and ${criterion.condition}
                </when>
                <when test="criterion.singleValue" >
                  and ${criterion.condition} #{criterion.value}
                </when>
                <when test="criterion.betweenValue" >
                  and ${criterion.condition} #{criterion.value} and #{criterion.secondValue}
                </when>
                <when test="criterion.listValue" >
                  and ${criterion.condition}
                  <foreach collection="criterion.value" item="listItem" open="(" close=")" separator="," >
                    #{listItem}
                  </foreach>
                </when>
              </choose>
            </foreach>
          </trim>
        </if>
      </foreach>
    </where>
  </sql>
  <sql id="Base_Column_List" >
    <!--
      WARNING - @mbggenerated
      This element is automatically generated by MyBatis Generator, do not modify.
    -->
    `id`, `tradePassword`, `usableAmount`, `freezedAmount`, `borrowLimitAmount`, `version`, 
    `unReceiveInterest`, `unReceivePrincipal`, `unReturnAmount`, `remainBorrowLimit`
  </sql>
  <select id="selectByExample" resultMap="BaseResultMap" parameterType="cn.carry.domain.AccountExample" >
    <!--
      WARNING - @mbggenerated
      This element is automatically generated by MyBatis Generator, do not modify.
    -->
    select
    <if test="distinct" >
      distinct
    </if>
    <include refid="Base_Column_List" />
    from `account`
    <if test="_parameter != null" >
      <include refid="Example_Where_Clause" />
    </if>
    <if test="orderByClause != null" >
      order by ${orderByClause}
    </if>
  </select>
  <delete id="deleteByExample" parameterType="cn.carry.domain.AccountExample" >
    <!--
      WARNING - @mbggenerated
      This element is automatically generated by MyBatis Generator, do not modify.
    -->
    delete from `account`
    <if test="_parameter != null" >
      <include refid="Example_Where_Clause" />
    </if>
  </delete>
  <insert id="insertSelective" parameterType="cn.carry.domain.Account" >
    <!--
      WARNING - @mbggenerated
      This element is automatically generated by MyBatis Generator, do not modify.
    -->
    insert into `account`
    <trim prefix="(" suffix=")" suffixOverrides="," >
      <if test="id != null" >
        `id`,
      </if>
      <if test="tradepassword != null" >
        `tradePassword`,
      </if>
      <if test="usableamount != null" >
        `usableAmount`,
      </if>
      <if test="freezedamount != null" >
        `freezedAmount`,
      </if>
      <if test="borrowlimitamount != null" >
        `borrowLimitAmount`,
      </if>
      <if test="version != null" >
        `version`,
      </if>
      <if test="unreceiveinterest != null" >
        `unReceiveInterest`,
      </if>
      <if test="unreceiveprincipal != null" >
        `unReceivePrincipal`,
      </if>
      <if test="unreturnamount != null" >
        `unReturnAmount`,
      </if>
      <if test="remainborrowlimit != null" >
        `remainBorrowLimit`,
      </if>
    </trim>
    <trim prefix="values (" suffix=")" suffixOverrides="," >
      <if test="id != null" >
        #{id,jdbcType=BIGINT},
      </if>
      <if test="tradepassword != null" >
        #{tradepassword,jdbcType=VARCHAR},
      </if>
      <if test="usableamount != null" >
        #{usableamount,jdbcType=DECIMAL},
      </if>
      <if test="freezedamount != null" >
        #{freezedamount,jdbcType=DECIMAL},
      </if>
      <if test="borrowlimitamount != null" >
        #{borrowlimitamount,jdbcType=DECIMAL},
      </if>
      <if test="version != null" >
        #{version,jdbcType=INTEGER},
      </if>
      <if test="unreceiveinterest != null" >
        #{unreceiveinterest,jdbcType=DECIMAL},
      </if>
      <if test="unreceiveprincipal != null" >
        #{unreceiveprincipal,jdbcType=DECIMAL},
      </if>
      <if test="unreturnamount != null" >
        #{unreturnamount,jdbcType=DECIMAL},
      </if>
      <if test="remainborrowlimit != null" >
        #{remainborrowlimit,jdbcType=DECIMAL},
      </if>
    </trim>
  </insert>
  <select id="countByExample" parameterType="cn.carry.domain.AccountExample" resultType="java.lang.Integer" >
    <!--
      WARNING - @mbggenerated
      This element is automatically generated by MyBatis Generator, do not modify.
    -->
    select count(*) from `account`
    <if test="_parameter != null" >
      <include refid="Example_Where_Clause" />
    </if>
  </select>
  <update id="updateByExampleSelective" parameterType="map" >
    <!--
      WARNING - @mbggenerated
      This element is automatically generated by MyBatis Generator, do not modify.
    -->
    update `account`
    <set >
      <if test="record.id != null" >
        `id` = #{record.id,jdbcType=BIGINT},
      </if>
      <if test="record.tradepassword != null" >
        `tradePassword` = #{record.tradepassword,jdbcType=VARCHAR},
      </if>
      <if test="record.usableamount != null" >
        `usableAmount` = #{record.usableamount,jdbcType=DECIMAL},
      </if>
      <if test="record.freezedamount != null" >
        `freezedAmount` = #{record.freezedamount,jdbcType=DECIMAL},
      </if>
      <if test="record.borrowlimitamount != null" >
        `borrowLimitAmount` = #{record.borrowlimitamount,jdbcType=DECIMAL},
      </if>
      <if test="record.version != null" >
        `version` = #{record.version,jdbcType=INTEGER},
      </if>
      <if test="record.unreceiveinterest != null" >
        `unReceiveInterest` = #{record.unreceiveinterest,jdbcType=DECIMAL},
      </if>
      <if test="record.unreceiveprincipal != null" >
        `unReceivePrincipal` = #{record.unreceiveprincipal,jdbcType=DECIMAL},
      </if>
      <if test="record.unreturnamount != null" >
        `unReturnAmount` = #{record.unreturnamount,jdbcType=DECIMAL},
      </if>
      <if test="record.remainborrowlimit != null" >
        `remainBorrowLimit` = #{record.remainborrowlimit,jdbcType=DECIMAL},
      </if>
    </set>
    <if test="_parameter != null" >
      <include refid="Update_By_Example_Where_Clause" />
    </if>
  </update>
  <update id="updateByExample" parameterType="map" >
    <!--
      WARNING - @mbggenerated
      This element is automatically generated by MyBatis Generator, do not modify.
    -->
    update `account`
    set `id` = #{record.id,jdbcType=BIGINT},
      `tradePassword` = #{record.tradepassword,jdbcType=VARCHAR},
      `usableAmount` = #{record.usableamount,jdbcType=DECIMAL},
      `freezedAmount` = #{record.freezedamount,jdbcType=DECIMAL},
      `borrowLimitAmount` = #{record.borrowlimitamount,jdbcType=DECIMAL},
      `version` = #{record.version,jdbcType=INTEGER},
      `unReceiveInterest` = #{record.unreceiveinterest,jdbcType=DECIMAL},
      `unReceivePrincipal` = #{record.unreceiveprincipal,jdbcType=DECIMAL},
      `unReturnAmount` = #{record.unreturnamount,jdbcType=DECIMAL},
      `remainBorrowLimit` = #{record.remainborrowlimit,jdbcType=DECIMAL}
    <if test="_parameter != null" >
      <include refid="Update_By_Example_Where_Clause" />
    </if>
  </update>
  <update id="updateByPrimaryKeySelective" parameterType="cn.carry.domain.Account" >
    <!--
      WARNING - @mbggenerated
      This element is automatically generated by MyBatis Generator, do not modify.
    -->
    update `account`
    <set >
      <if test="tradepassword != null" >
        `tradePassword` = #{tradepassword,jdbcType=VARCHAR},
      </if>
      <if test="usableamount != null" >
        `usableAmount` = #{usableamount,jdbcType=DECIMAL},
      </if>
      <if test="freezedamount != null" >
        `freezedAmount` = #{freezedamount,jdbcType=DECIMAL},
      </if>
      <if test="borrowlimitamount != null" >
        `borrowLimitAmount` = #{borrowlimitamount,jdbcType=DECIMAL},
      </if>
      <if test="version != null" >
        `version` = #{version,jdbcType=INTEGER},
      </if>
      <if test="unreceiveinterest != null" >
        `unReceiveInterest` = #{unreceiveinterest,jdbcType=DECIMAL},
      </if>
      <if test="unreceiveprincipal != null" >
        `unReceivePrincipal` = #{unreceiveprincipal,jdbcType=DECIMAL},
      </if>
      <if test="unreturnamount != null" >
        `unReturnAmount` = #{unreturnamount,jdbcType=DECIMAL},
      </if>
      <if test="remainborrowlimit != null" >
        `remainBorrowLimit` = #{remainborrowlimit,jdbcType=DECIMAL},
      </if>
    </set>
    where `id` = #{id,jdbcType=BIGINT}
  </update>
</mapper>